MINARI_airflow_utils_pip/MINARI_airflow_utils_pip.py
MINARI_airflow_utils_pip/__init__.py
MINARI_airflow_utils_pip-0.1.0.dist-info/LICENSE
MINARI_airflow_utils_pip-0.1.0.dist-info/METADATA
MINARI_airflow_utils_pip-0.1.0.dist-info/WHEEL
MINARI_airflow_utils_pip-0.1.0.dist-info/entry_points.txt
MINARI_airflow_utils_pip-0.1.0.dist-info/top_level.txt
MINARI_airflow_utils_pip-0.1.0.dist-info/RECORD
