Metadata-Version: 2.1
Name: MINARI-airflow-utils-pip
Version: 0.1.0
Summary: practice
Home-page: https://blahxblah.github.io/MINARI_airflow_utils
Author: kjuheon
Author-email: id.blahxblah@gmail.com
License: GNU General Public License (GPL)
Project-URL: Bug Tracker, https://github.com/blahxblah/MINARI_airflow_utils/issues
Platform: macOS
Classifier: Programming Language :: Python :: 3
Classifier: License :: OSI Approved :: GNU General Public License (GPL)
Classifier: Operating System :: OS Independent
Requires-Python: >=3.6
License-File: LICENSE
